tests/__init__.py
tests/components.py
tests/conftest.py
tests/core/__init__.py
tests/core/test_api/__init__.py
tests/core/test_api/test_client.py
tests/core/test_api/test_endpoints.py
tests/core/test_api/test_keyphrase.py
tests/core/test_dataset/__init__.py
tests/core/test_dataset/test_dataset.py
tests/core/test_dataset/test_field.py
tests/core/test_dataset/test_keyphrase.py
tests/core/test_engine/__init__.py
tests/core/test_engine/test_engine.py
tests/core/test_engine/test_engine_playground.py
tests/core/test_engine/test_multipass_engine.py
tests/core/test_engine/test_stable_engine.py
tests/core/test_operator/__init__.py
tests/core/test_operator/test_document_diff.py
tests/core/test_workflow/__init__.py
tests/core/test_workflow/test_workflow.py
workflows_core/__init__.py
workflows_core/config.py
workflows_core/constants.py
workflows_core/errors.py
workflows_core/helpers.py
workflows_core/types.py
workflows_core/api/__init__.py
workflows_core/api/api.py
workflows_core/api/client.py
workflows_core/api/endpoints.py
workflows_core/api/helpers.py
workflows_core/components/__init__.py
workflows_core/components/components.py
workflows_core/dataset/__init__.py
workflows_core/dataset/dataset.py
workflows_core/dataset/field.py
workflows_core/engine/__init__.py
workflows_core/engine/abstract_engine.py
workflows_core/engine/cluster_engine.py
workflows_core/engine/multipass_engine.py
workflows_core/engine/ray_engine.py
workflows_core/engine/small_batch_stable_engine.py
workflows_core/engine/stable_engine.py
workflows_core/operator/__init__.py
workflows_core/operator/abstract_operator.py
workflows_core/operator/ray_operator.py
workflows_core/utils/__init__.py
workflows_core/utils/document.py
workflows_core/utils/document_list.py
workflows_core/utils/encode_parameters.py
workflows_core/utils/example_documents.py
workflows_core/utils/json_encoder.py
workflows_core/utils/keyphrase.py
workflows_core/utils/seed.py
workflows_core/workflow/__init__.py
RelevanceAI_Workflows_Core-0.22.2.dist-info/LICENSE
RelevanceAI_Workflows_Core-0.22.2.dist-info/METADATA
RelevanceAI_Workflows_Core-0.22.2.dist-info/WHEEL
RelevanceAI_Workflows_Core-0.22.2.dist-info/top_level.txt
RelevanceAI_Workflows_Core-0.22.2.dist-info/RECORD
